LICENSE
MANIFEST.in
README.md
setup.cfg
setup.py
drf_spirit/__init__.py
drf_spirit/admin.py
drf_spirit/apps.py
drf_spirit/config.py
drf_spirit/emails.py
drf_spirit/fields.py
drf_spirit/filters.py
drf_spirit/models.py
drf_spirit/permissions.py
drf_spirit/relations.py
drf_spirit/serializers.py
drf_spirit/signals.py
drf_spirit/urls.py
drf_spirit/views.py
drf_spirit.egg-info/PKG-INFO
drf_spirit.egg-info/SOURCES.txt
drf_spirit.egg-info/dependency_links.txt
drf_spirit.egg-info/requires.txt
drf_spirit.egg-info/top_level.txt
drf_spirit/migrations/0001_initial.py
drf_spirit/migrations/0002_auto_20170324_1109.py
drf_spirit/migrations/0003_auto_20170324_1325.py
drf_spirit/migrations/0004_auto_20170406_1344.py
drf_spirit/migrations/0005_topic_is_archived.py
drf_spirit/migrations/0006_topic_description.py
drf_spirit/migrations/0007_auto_20170427_1232.py
drf_spirit/migrations/__init__.py
drf_spirit/templates/drf_spirit/new_comment.html
drf_spirit/tests/__init__.py
drf_spirit/tests/settings.py
drf_spirit/tests/test_category.py
drf_spirit/tests/urls.py
drf_spirit/tests/utils.py