Metadata-Version: 1.1
Name: drf-spirit
Version: 0.0.2
Summary: A pluggable django forum application build with Django Rest Framework
Home-page: https://github.com/alaminopu/drf-spirit
Author: Md. Al-Amin Opu
Author-email: alamin.opu10@gmail.com
License: MIT License
Keywords: forum,drf forum,API Based forum
Platform: UNKNOWN
Classifier: Environment :: Web Environment
Classifier: Framework :: Django
Classifier: Framework :: Django :: 1.8
Classifier: Intended Audience :: Developers
Classifier: Operating System :: OS Independent
Classifier: Programming Language :: Python
Classifier: Programming Language :: Python :: 2
Classifier: Programming Language :: Python :: 2.7
Classifier: Programming Language :: Python :: 3
Classifier: Topic :: Internet :: WWW/HTTP
Classifier: Topic :: Internet :: WWW/HTTP :: Dynamic Content
